cn_price_formatter/__init__.py
cn_price_formatter/price_formatter.py
tests/__init__.py
tests/didatravel_test_price_formatter.py
tests/exp_test_price_formatter.py
tests/hp_price_formatter.py
tests/rakuten_price_formatter.py
tests/ratehawk_price_formatter.py
tests/tboholidays_test_price_formatter.py
cn_price_formatter-0.1.10.dist-info/METADATA
cn_price_formatter-0.1.10.dist-info/WHEEL
cn_price_formatter-0.1.10.dist-info/top_level.txt
cn_price_formatter-0.1.10.dist-info/RECORD
