Metadata-Version: 2.1
Name: cn-price-formatter
Version: 0.1.10
Summary: This package provides a PriceFormatter class for handling and formatting hotel pricing data.
Home-page: UNKNOWN
Author: M Usman Tahir
Author-email: usman@cuddlynest.com
License: UNKNOWN
Platform: UNKNOWN
